modelformhistory/__init__.py
modelformhistory/admin.py
modelformhistory/apps.py
modelformhistory/forms.py
modelformhistory/helpers.py
modelformhistory/models.py
modelformhistory/views.py
modelformhistory/locale/fr_FR/LC_MESSAGES/django.mo
modelformhistory/locale/fr_FR/LC_MESSAGES/django.po
modelformhistory/migrations/0001_initial.py
modelformhistory/migrations/0002_auto_20190626_0321.py
modelformhistory/migrations/0003_auto_20190626_0938.py
modelformhistory/migrations/__init__.py
django_modelformhistory-1.0.11.dist-info/AUTHORS.md
django_modelformhistory-1.0.11.dist-info/METADATA
django_modelformhistory-1.0.11.dist-info/WHEEL
django_modelformhistory-1.0.11.dist-info/top_level.txt
django_modelformhistory-1.0.11.dist-info/RECORD
