Metadata-Version: 2.1
Name: django-modelformhistory
Version: 1.0.11
Summary: UNKNOWN
Home-page: https://github.com/EngageSports/django-modelformhistory
Author: Martyn CLEMENT
Author-email: martyn.clement@gmail.com
License: UNKNOWN
Platform: UNKNOWN
Classifier: Environment :: Web Environment
Classifier: Framework :: Django
Classifier: Intended Audience :: Developers
Classifier: License :: OSI Approved :: BSD License
Classifier: Operating System :: OS Independent
Classifier: Programming Language :: Python
Classifier: Topic :: Software Development :: Libraries :: Python Modules
